<?xml version="1.0" encoding="UTF-8"?><database>
    <element label="CP SFTP" max_length="40" name="x_305439_digital_m_cp_sftp" type="collection">
        <element calculation="(function calculatedFieldValue(current) {&#13;&#10;&#13;&#10;&#9;// Add your code here&#13;&#10;&#9;return '';  // return the calculated value&#13;&#10;&#13;&#10;})(current);" choice="1" label="Key Alias" max_length="40" name="key_alias" type="choice">
            <choice/>
        </element>
        <element calculation="(function calculatedFieldValue(current) {&#13;&#10;&#13;&#10;&#9;// Add your code here&#13;&#10;&#9;return '';  // return the calculated value&#13;&#10;&#13;&#10;})(current);" label="Login name" max_length="64" name="login_name" type="string"/>
        <element calculation="(function calculatedFieldValue(current) {&#13;&#10;&#13;&#10;&#9;// Add your code here&#13;&#10;&#9;return '';  // return the calculated value&#13;&#10;&#13;&#10;})(current);" choice="3" default="PUBLIC_KEY" hint="Select the authentication type which will be used by the client to login on the remote server." label="Login type" max_length="40" name="login_type" type="choice">
            <choice>
                <element inactive_on_update="false" label="SSH Key" sequence="1" value="PUBLIC_KEY"/>
                <element inactive_on_update="false" label="Password" sequence="2" value="PASSWORD"/>
            </choice>
        </element>
        <element calculation="(function calculatedFieldValue(current) {&#13;&#10;&#13;&#10;&#9;// Add your code here&#13;&#10;&#9;return '';  // return the calculated value&#13;&#10;&#13;&#10;})(current);" label="Password" max_length="255" name="password" type="password2"/>
        <element calculation="(function calculatedFieldValue(current) {&#13;&#10;&#13;&#10;&#9;// Add your code here&#13;&#10;&#9;return '';  // return the calculated value&#13;&#10;&#13;&#10;})(current);" label="SSH Key" max_length="40" name="ssh_key" type="file_attachment"/>
    </element>
</database>
